sparrow/loader/__init__.py
sparrow/loader/cli.py
sparrow/loader/converter.py
sparrow/loader/display.py
sparrow/loader/fields.py
sparrow/loader/interface.py
sparrow/loader/schema.py
sparrow/loader/schema_checking.py
sparrow/loader/sparrow-db-models.pickle
sparrow/loader/test_schema_checking.py
sparrow/loader/util.py
sparrow_loader-1.0.8.dist-info/entry_points.txt
sparrow_loader-1.0.8.dist-info/WHEEL
sparrow_loader-1.0.8.dist-info/METADATA
sparrow_loader-1.0.8.dist-info/RECORD
