Metadata-Version: 2.1
Name: sparrow-loader
Version: 1.0.8
Summary: Utilities for loading data into Sparrow
License: MIT
Author: Daven Quinn
Author-email: dev@davenquinn.com
Requires-Python: >=3.9,<4.0
Classifier: License :: OSI Approved :: MIT License
Classifier: Programming Language :: Python :: 3
Classifier: Programming Language :: Python :: 3.9
Classifier: Programming Language :: Python :: 3.10
Requires-Dist: GeoAlchemy2 (>=0.9.4,<0.10.0)
Requires-Dist: SQLAlchemy (>=1.4.41,<2.0.0)
Requires-Dist: macrostrat.database (>=1.0.2,<2.0.0)
Requires-Dist: marshmallow (>=3.11.1,<4.0.0)
Requires-Dist: marshmallow-jsonschema (>=0.10.0,<0.11.0)
Requires-Dist: marshmallow-sqlalchemy (>=0.24.2,<0.25.0)
Requires-Dist: rich (>=12.6.0,<13.0.0)
Requires-Dist: shapely (>=1,<2)
Requires-Dist: stringcase (>=1.2.0,<2.0.0)
Requires-Dist: typer (>=0.6.1,<0.7.0)
